{"note":"Don't delete this file! It's used internally to help with page regeneration.","tagline":"Pages repository","name":"Pedro Jordano @ github.com","body":"![banner](http://ebd10.ebd.csic.es/groups/pjlab/wiki/welcome/images/19b1a.png)\r\n### Welcome to Pedro Jordano Lab Pages @[GitHub](http://github.com).\r\n\r\nThis is a repository for project pages and material related to coding, mostly R, MATLAB and python. More info can be obtained in the [Pedro Jordano Lab Home](http://ebd10.ebd.csic.es) or [Pedro's Home Page](http://ebd10.ebd.csic.es/ebd10/Pedro.html).\r\n\r\n-- Pedro\r\n\r\n***\r\n### Project pages\r\n1. [Plotting effectiveness landscapes](http://pedroj.github.com/effectiveness/). To accompany: Schupp, E.W., Jordano, P. & Gomez, J.M. (2010). Seed dispersal effectiveness revisited: a conceptual review. New Phytol, 188, 333–353.","google":""}